txdlo/__init__.py
txdlo/dlo.py
txdlo-0.1.8.dist-info/DESCRIPTION.rst
txdlo-0.1.8.dist-info/METADATA
txdlo-0.1.8.dist-info/pydist.json
txdlo-0.1.8.dist-info/RECORD
txdlo-0.1.8.dist-info/top_level.txt
txdlo-0.1.8.dist-info/WHEEL
