Metadata-Version: 2.0
Name: txdlo
Version: 0.1.8
Summary: A Twisted class for observing a set of deferreds.
Home-page: https://github.com/terrycojones/txdlo
Author: Terry Jones
Author-email: terry@jon.es
License: UNKNOWN
Download-URL: https://github.com/terrycojones/txdlo
Keywords: twisted deferred observer
Platform: UNKNOWN
Classifier: Programming Language :: Python
Classifier: Framework :: Twisted
Classifier: Development Status :: 4 - Beta
Classifier: Intended Audience :: Developers
Classifier: License :: OSI Approved :: Apache Software License
Classifier: Operating System :: OS Independent
Classifier: Topic :: Software Development :: Libraries :: Python Modules
Provides: txdlo
Requires-Dist: Twisted
